easy_widgets/Application.py
easy_widgets/Dialog.py
easy_widgets/Menu.py
easy_widgets/MenuBox.py
easy_widgets/MessageBox.py
easy_widgets/Table.py
easy_widgets/TextInput.py
easy_widgets/Widget.py
easy_widgets/Wizzard.py
easy_widgets/__init__.py
easy_widgets-0.3.dist-info/METADATA
easy_widgets-0.3.dist-info/WHEEL
easy_widgets-0.3.dist-info/top_level.txt
easy_widgets-0.3.dist-info/RECORD
