Metadata-Version: 2.4
Name: easy_widgets
Version: 0.3
Summary: Make widget management in CLI easy
Home-page: https://github.com/fantastic001/easy_widgets
Download-URL: https://github.com/fantastic001/easy_widgets/tarball/0.2
Author: Stefan Nožinić
Author-email: stefan@lugons.org
License: MIT
Keywords: curses,CLI,widgets
Classifier: Development Status :: 4 - Beta
Classifier: Intended Audience :: Developers
Classifier: License :: OSI Approved :: MIT License
Classifier: Programming Language :: Python :: 3
Classifier: Programming Language :: Python :: 3.7
Classifier: Programming Language :: Python :: 3.8
Classifier: Programming Language :: Python :: 3.9
Classifier: Programming Language :: Python :: 3.10
Requires-Python: >=3.7
Requires-Dist: urwid>=3.0.0
Dynamic: author
Dynamic: author-email
Dynamic: classifier
Dynamic: description
Dynamic: description-content-type
Dynamic: download-url
Dynamic: home-page
Dynamic: keywords
Dynamic: license
Dynamic: requires-dist
Dynamic: requires-python
Dynamic: summary
